setup.py
shrine/__init__.py
shrine/basics.py
shrine/bin.py
shrine/boot.py
shrine/conf.py
shrine/controllers.py
shrine/engine.py
shrine/init.py
shrine/loader.py
shrine/log.py
shrine/mailgun.py
shrine/manage.py
shrine/models.py
shrine/routes.py
shrine/settings.py
shrine/shell.py
shrine/testing.py
shrine/views.py
shrine/web.py
shrine.egg-info/PKG-INFO
shrine.egg-info/SOURCES.txt
shrine.egg-info/dependency_links.txt
shrine.egg-info/entry_points.txt
shrine.egg-info/requires.txt
shrine.egg-info/top_level.txt
shrine/apps/__init__.py
shrine/apps/core/__init__.py
shrine/cmds/__init__.py
shrine/cmds/create.py
shrine/cmds/registry.py
shrine/cmds/run.py
shrine/cmds/shell.py
shrine/cmds/syncdb.py
shrine/skel/.gitignore
shrine/skel/Procfile
shrine/skel/README.md
shrine/skel/__init__.py
shrine/skel/manage.py
shrine/skel/requirements.txt
shrine/skel/settings.py
shrine/skel/controllers/index.py
shrine/skel/media/css/bootstrap-responsive.css
shrine/skel/media/css/bootstrap-responsive.min.css
shrine/skel/media/css/bootstrap.css
shrine/skel/media/css/bootstrap.min.css
shrine/skel/media/img/glyphicons-halflings-white.png
shrine/skel/media/img/glyphicons-halflings.png
shrine/skel/media/js/bootstrap.js
shrine/skel/media/js/bootstrap.min.js
shrine/skel/templates/index.html