Metadata-Version: 1.0
Name: shrine
Version: 0.0.24
Summary: Tornado + Django
Home-page: http://falcao.it/shrine
Author: Gabriel Falcao
Author-email: gabriel@nacaolivre.org
License: UNKNOWN
Platform: UNKNOWN
